protein_detective/__init__.py
protein_detective/__version__.py
protein_detective/cli.py
protein_detective/db.py
protein_detective/ddl.sql
protein_detective/filter.py
protein_detective/py.typed
protein_detective/utils.py
protein_detective/visualization.py
protein_detective/workflow.py
protein_detective/powerfit/__init__.py
protein_detective/powerfit/cli.py
protein_detective/powerfit/options.py
protein_detective/powerfit/parallel.py
protein_detective/powerfit/run.py
protein_detective/powerfit/solution.py
protein_detective/powerfit/workflow.py
protein_detective-0.4.0.dist-info/METADATA
protein_detective-0.4.0.dist-info/WHEEL
protein_detective-0.4.0.dist-info/entry_points.txt
protein_detective-0.4.0.dist-info/licenses/LICENSE
protein_detective-0.4.0.dist-info/RECORD
