Metadata-Version: 2.4
Name: protein_detective
Version: 0.4.0
Summary: Deduce the protein from a EM density
Project-URL: Homepage, https://github.com/haddocking/protein-detective
Project-URL: Issues, https://github.com/haddocking/protein-detective/issues
Project-URL: Documentation, https://www.bonvinlab.org/protein-detective/
Project-URL: Source, https://github.com/haddocking/protein-detective
License-File: LICENSE
Requires-Python: >=3.13
Requires-Dist: aiofiles>=24.1.0
Requires-Dist: aiohttp-retry>=2.9.1
Requires-Dist: aiohttp>=3.11.18
Requires-Dist: attrs>=25.3.0
Requires-Dist: bokeh>=3.7.3
Requires-Dist: cattrs>=24.1.3
Requires-Dist: dask>=2025.5.1
Requires-Dist: distributed>=2025.5.1
Requires-Dist: duckdb>=1.2.2
Requires-Dist: molviewspec>=1.6.0
Requires-Dist: pandas>=2.3.0
Requires-Dist: powerfit-em[opencl]>=3.0.6
Requires-Dist: protein-quest>=0.3.3
Requires-Dist: psutil>=7.0.0
Requires-Dist: rich-argparse>=1.7.1
Requires-Dist: rich>=14.0.0
Requires-Dist: sparqlwrapper>=2.0.0
Requires-Dist: tqdm>=4.67.1
Requires-Dist: urllib3>=2.4.0
